Workbook

Sheet 1_Dashboard
A2: DPP-ADAPT: This is the steering committee dashboard. All values are pulled from phase sheets; edit phase sheets, charts and tiles auto-update on recalc.
B4: Phase progress | C4: P0 | D4: P1 | E4: P2 | F4: P3 | G4: P4 | H4: P5 | I4: P6
C5: ='3_P0_Readiness'!B6 -> Open | D5: ='5_P1_Scope'!B6 -> Open | E5: ='6_P2_Touchpoints'!B6 -> Open | F5: ='8_P3_Mapping'!B6 -> Open | G5: ='10_P4_Pattern'!B6 -> Open | H5: ='11_P5_Roadmap'!B6 -> Open | I5: ='12_P6_Evaluation'!B6 -> Open
B7: Readiness (P0) | K7: Readiness radar
B8: Data | C8: ='3_P0_Readiness'!H10 -> 3.8
B9: Process | C9: ='3_P0_Readiness'!H15 -> 3.8
B10: Governance | C10: ='3_P0_Readiness'!H20 -> 3.8
B11: Application | C11: ='3_P0_Readiness'!H25 -> 4.4
B12: External Ecosystem | C12: ='3_P0_Readiness'!H30 -> 3.6
B13: Overall | C13: =AVERAGE(C8:C12) -> 3.88 | D13: Rating | E13: =IF(C13<2,"Low",IF(C13<=3.5,"Medium","High")) -> High
B15: Integration pattern (P4)
B16: Chosen pattern | C16: ='10_P4_Pattern'!C22 -> C: Dataspace connector
B17: Weighted total | C17: ='10_P4_Pattern'!C23 -> 4
B18: Statement | C18: ='10_P4_Pattern'!B25 -> The following statement relies on availability of the chosen infrastructure. Fraunhofer ISST scores Pattern C highest: 117 notebook users on a 3 to4 year refresh (€200–400K/cycle) running on SAP S/4HANA + SAP Ariba via central Fraunhofer ICT and Microsoft Entra ID, combined with in-house dataspace expertise and existing Kubernetes capability. Pattern A is retained as a contingency. It depends on whether the market/regulatory body has made the infrastructure available..
B20: Indicators (P6) | K20: Attribute combined scores
B21: Mapping coverage (%) | C21: =IFERROR(COUNTIF('8_P3_Mapping'!K10:K30,"Approved")/COUNTA('8_P3_Mapping'!B10:B30),0)*100 -> 33.333333
B22: Touchpoints active | C22: =COUNTIF('6_P2_Touchpoints'!C10:H17,">0") -> 9
B23: Approved attributes | C23: =COUNTIF('7_P2_Attributes'!L12:L21,"Use as criterion") -> 4
B24: Risks — Red | C24: =COUNTIF('11_P5_Roadmap'!P37:P57,"Red") -> 0
B25: Risks — Amber | C25: =COUNTIF('11_P5_Roadmap'!P37:P57,"Amber") -> 6
B26: Risks — Green | C26: =COUNTIF('11_P5_Roadmap'!P37:P57,"Green") -> 1
B28: Legend
B29: Blue text | C29: Hardcoded input
B30: Black text | C30: Formula — do not overwrite
B31: Green text | C31: Cross-sheet link
B32: Yellow / Amber fill | C32: Needs attention
B33: Red fill | C33: Failure / blocked / red risk
B34: Green fill | C34: Passed / approved / green risk

Sheet 2_Method_Map
A1: DPP-ADAPT — Method map and instructions
B3: Phase | C3: Purpose | D3: Sheet(s)
B4: P0 Preliminary | C4: Assess readiness, set governance and decision rights. | D4: 3, 4
B5: P1 Architecture Vision | C5: Confirm motivation, choose product family, capability gap | D5: 5
B6: P2 Business Architecture | C6: Touchpoints and DPP attribute scoring, procurement-use role | D6: 6, 7
B7: P3 Information & Appl. | C7: Semantic mapping, application inventory | D7: 8, 9
B8: P4 Technology Pattern | C8: Pattern selection scoring across 7 dimensions (3 patterns: 1 Manual look-up, 2a Central database, 2b Dataspace connector) | D8: 10
B9: P5 Transition | C9: Roadmap with plateaus, work packages, risks | D9: 11
B10: P6 Implementation Gov. | C10: Governance, indicators, evaluation. | D10: 12
B13: Conventions
B14: • Blue text = hardcoded inputs. Black = formulas. Green = cross-sheet links.
B15: • Each phase sheet has a sign-off cell at B6 (drop-down: Open / In review / Signed off).
B16: • Dashboard phase tiles pull directly from these sign-off cells.
B17: • Scoring scales are 1 (low) to 5 (high) unless otherwise indicated in the sheet header.
B18: • Cell comments (red corner) document formulas, thresholds, and provenance.
B20: Default weights and rationale
B21: All justifications of scoring logic and choice of EA and PM tools can be found in the final thesis doc.
B22: Sheet 7: attribute scoring (Combined = 0.4 R + 0.4 E + 0.2 V)
B23: Relevance at 0.40 | C23: Whether the attribute speaks to a procurement-relevant sustainability concern. If irrelevant, the data is uninteresting regardless of how reliable it is. Equal weight with Evidence reflects that both are necessary conditions.
B24: Evidence confidence at 0.40 | C24: Whether DPP and supporting sources can actually provide the value with traceable provenance. Independent of relevance, so it must hold separately and is weighted equally.
B25: Verifiability at 0.20 | C25: Whether the authority and external bodies can re-test or audit the claim. Lower weight than R and E because partial verifiability can be compensated by procurement-process safeguards (e.g., self-declaration + spot checks). Treated as a quality dimension rather than a precondition.
B27: Sheet 10: pattern selection (weighted sum across 7 dimensions)
B28: Readiness fit at 0.20 | C28: Highest tier together with use-case fit. DR1 makes readiness the binding constraint: choosing a pattern beyond readiness fails in delivery.
B29: Use-case fit at 0.20 | C29: Highest tier. A pattern that does not fit the chosen touchpoints (P2) wastes investment regardless of how mature the authority is.
B30: Governance load at 0.15 (inverted) | C30: Mid tier. Governance overhead consumes capacity. Inverted so that low load → high score.
B31: Total cost at 0.15 (inverted) | C31: Mid tier. Public-sector budgets are finite. Inverted so that low cost → high score.
B32: Volume scalability at 0.10 | C32: Lower tier for a first implementation: most first implementations are low-volume.
B33: Time-to-value at 0.10 (inverted) | C33: Lower tier: agility matters but the method explicitly stages first implementations. Inverted.
B34: Future-proofness vs EU portal at 0.10 | C34: Lower tier: the trajectory of EU portal mechanisms is uncertain. Weighted enough to influence ties but not to dominate decisions whose horizon is short.
B36: Weights are configurable per project and have been chosen according to the researchers preference of which defaults reflect the rationale above. Sums must equal 1.00 (enforced on Sheet 10).

Sheet 3_P0_Readiness
A1: P0 – Preliminary: readiness and setup
A2: Purpose | B2: Assess readiness across five dimensions to inform operating-model and pattern range.
A3: Inputs from | B3: Procurement and sustainability strategy; application inventory; sponsor candidates.
A4: Outputs to | B4: Readiness band → Sheet 1 dashboard; recommended pattern range → Sheet 10.
A5: RACI summary | B5: R: Enterprise Architect; A: Sponsor; C: Procurement Lead, IT Integration Lead; I: All.
A6: Phase sign-off | B6: Open | C6: Signed by | E6: please fill | G6: Date | H6: please fill
A8: Readiness self-assessment (25 statements = 5 statements × 5 dimensions; 1=Disagree to 5=Agree)
B9: Dimension | C9: Statement | D9: Evidence source | E9: Score (1–5) | F9: Weight | G9: Weighted | H9: Dim avg
B10: Data | C10: We have a product master with consistent identifiers. | D10: please fill | E10: 4 | F10: 1 | G10: =E10*F10 -> 4 | H10: =AVERAGE(G10:G14)/AVERAGE(F10:F14) -> 3.8
B11: Data | C11: We have a defined data-quality process for supplier-provided data. | D11: please fill | E11: 4 | F11: 1 | G11: =E11*F11 -> 4
B12: Data | C12: We can store and retrieve attribute snapshots persistently. | D12: please fill | E12: 4 | F12: 1 | G12: =E12*F12 -> 4
B13: Data | C13: We use a controlled vocabulary for product attributes. | D13: please fill | E13: 3 | F13: 1 | G13: =E13*F13 -> 3
B14: Data | C14: We have a data entry role assigned. | D14: please fill | E14: 4 | F14: 1 | G14: =E14*F14 -> 4
B15: Process | C15: Our procurement process is documented end-to-end. | D15: please fill | E15: 4 | F15: 1 | G15: =E15*F15 -> 4 | H15: =AVERAGE(G15:G19)/AVERAGE(F15:F19) -> 3.8
B16: Process | C16: We have repeatable practice for sustainable specifications. | D16: please fill | E16: 3 | F16: 1 | G16: =E16*F16 -> 3
B17: Process | C17: We have post-award verification practice. | D17: please fill | E17: 4 | F17: 1 | G17: =E17*F17 -> 4
B18: Process | C18: We can distinguish exclusion, qualification, and award criteria operationally. | D18: please fill | E18: 4 | F18: 1 | G18: =E18*F18 -> 4
B19: Process | C19: We capture evidence in a structured tender file. | D19: please fill | E19: 4 | F19: 1 | G19: =E19*F19 -> 4
B20: Governance | C20: We have defined decision rights for procurement IT changes. | D20: please fill | E20: 4 | F20: 1 | G20: =E20*F20 -> 4 | H20: =AVERAGE(G20:G24)/AVERAGE(F20:F24) -> 3.8
B21: Governance | C21: We have a sponsor and steering committee model. | D21: please fill | E21: 4 | F21: 1 | G21: =E21*F21 -> 4
B22: Governance | C22: We coordinate with legal on contestable criteria. | D22: please fill | E22: 4 | F22: 1 | G22: =E22*F22 -> 4
B23: Governance | C23: We have a change management process for procurement tools. | D23: please fill | E23: 4 | F23: 1 | G23: =E23*F23 -> 4
B24: Governance | C24: We have an internal-audit relationship for procurement records. | D24: please fill | E24: 3 | F24: 1 | G24: =E24*F24 -> 3
B25: Application | C25: Our e-procurement platform supports extensions or APIs. | D25: please fill | E25: 5 | F25: 1 | G25: =E25*F25 -> 5 | H25: =AVERAGE(G25:G29)/AVERAGE(F25:F29) -> 4.4
B26: Application | C26: We have an integration capability (broker or hub). | D26: please fill | E26: 4 | F26: 1 | G26: =E26*F26 -> 4
B27: Application | C27: Our applications expose APIs for procurement data. | D27: please fill | E27: 4 | F27: 1 | G27: =E27*F27 -> 4
B28: Application | C28: We have authentication and authorisation across procurement applications. | D28: please fill | E28: 5 | F28: 1 | G28: =E28*F28 -> 5
B29: Application | C29: We can audit-log access to procurement data. | D29: please fill | E29: 4 | F29: 1 | G29: =E29*F29 -> 4
B30: External | C30: We monitor EU DPP regulatory developments. | D30: please fill | E30: 5 | F30: 1 | G30: =E30*F30 -> 5 | H30: =AVERAGE(G30:G34)/AVERAGE(F30:F34) -> 3.6
B31: External | C31: We have channels to relevant standards bodies. | D31: please fill | E31: 4 | F31: 1 | G31: =E31*F31 -> 4
B32: External | C32: We have liaison with market surveillance authorities. | D32: please fill | E32: 3 | F32: 1 | G32: =E32*F32 -> 3
B33: External | C33: We engage suppliers on DPP readiness. | D33: please fill | E33: 3 | F33: 1 | G33: =E33*F33 -> 3
B34: External | C34: We have ICT supplier-base maturity to support DPP attributes. | D34: please fill | E34: 3 | F34: 1 | G34: =E34*F34 -> 3
A36: Overall readiness summary
B37: Overall score | C37: =AVERAGE(H10,H15,H20,H25,H30) -> 3.88 | D37: Maturity level | E37: =IF(C37<2,"Low",IF(C37<=3.5,"Medium","High")) -> High | F37: Recom-mended pattern range | G37: =IF(C37<2,"A only",IF(C37<=3.5,"A or B","B or C")) -> B or C

Sheet 4_P0_RACI
A1: P0 – Stakeholders and RACI
A2: Purpose | B2: Identify stakeholders and assign decision rights using RACI.
A3: Inputs from | B3: Project group nomination; existing governance structures.
A4: Outputs to | B4: Approved RACI used throughout P1–P6.
A5: RACI summary | B5: R: Project Manager; A: Sponsor; C: All roles; I: External liaisons.
A6: Phase sign-off | B6: Open | C6: Signed by | E6: please fill | G6: Date | H6: please fill
A8: Stakeholder register
B9: Name / placeholder | C9: Organisation / unit | D9: Role | E9: Internal/External | F9: Interest (1–5) | G9: Influence (1–5) | H9: Influence
B10: Procurement Lead | C10: please fill | D10: Owner of in-scope tender | E10: Internal | F10: 5 | G10: 5 | H10: =F10*G10 -> 25
B11: Sustainability Lead | C11: please fill | D11: Owner of sustainability objectives | E11: Internal | F11: 5 | G11: 4 | H11: =F11*G11 -> 20
B12: Legal Counsel | C12: please fill | D12: Procurement-law assurance | E12: Internal | F12: 4 | G12: 5 | H12: =F12*G12 -> 20
B13: Enterprise Architect | C13: please fill | D13: Owner of architectural views | E13: Internal | F13: 5 | G13: 4 | H13: =F13*G13 -> 20
B14: Data Steward | C14: please fill | D14: Owner of semantic mapping | E14: Internal | F14: 5 | G14: 3 | H14: =F14*G14 -> 15
B15: IT Integration Lead | C15: please fill | D15: Owner of integration realisation | E15: Internal | F15: 4 | G15: 4 | H15: =F15*G15 -> 16
B16: Funding sign-off | C16: please fill | D16: Institute-level sign-off and funding | E16: Internal | F16: 5 | G16: 5 | H16: =F16*G16 -> 25
B17: Market Surveillance Liaison | C17: please fill | D17: Liaison to surveillance | E17: External | F17: 3 | G17: 4 | H17: =F17*G17 -> 12
A19: RACI matrix (R Responsible, A Accountable, C Consulted, I Informed)
B20: Activity cluster | C20: Phase | D20: Proc.Lead | E20: Sustain.Lead | F20: Legal | G20: EA | H20: Data Stwd | I20: IT Int. | J20: Sponsor | K20: MS Liaison
B21: Readiness self-assessment | C21: P0 | D21: C | E21: C | F21: C | G21: R | H21: C | I21: C | J21: A | K21: I
B22: Stakeholder & RACI | C22: P0 | D22: R | E22: C | F22: C | G22: C | H22: C | I22: C | J22: A | K22: I
B23: Scope & motivation | C23: P1 | D23: R | E23: R | F23: C | G23: C | H23: C | I23: C | J23: A | K23: I
B24: Capability gap, views V1–V2 | C24: P1 | D24: C | E24: C | F24: C | G24: R | H24: C | I24: C | J24: A | K24: I
B25: Touchpoint matrix | C25: P2 | D25: R | E25: C | F25: C | G25: C | H25: C | I25: C | J25: A | K25: I
B26: Attribute scoring | C26: P2 | D26: C | E26: R | F26: C | G26: C | H26: R | I26: C | J26: A | K26: I
B27: Procurement-use role decisions | C27: P2 | D27: C | E27: C | F27: R | G27: C | H27: C | I27: C | J27: A | K27: I
B28: Semantic mapping | C28: P3 | D28: C | E28: C | F28: C | G28: C | H28: R | I28: C | J28: A | K28: I
B29: Application & info inventory, V4 | C29: P3 | D29: C | E29: C | F29: C | G29: R | H29: C | I29: R | J29: A | K29: I
B30: Pattern scoring & V5 | C30: P4 | D30: C | E30: C | F30: C | G30: R | H30: C | I30: R | J30: A | K30: I
B31: Roadmap, work packages | C31: P5 | D31: C | E31: C | F31: C | G31: C | H31: C | I31: C | J31: A | K31: I
... B33: Indicators & evaluation | C33: P6 | D33: R | E33: C | F33: C | G33: C | H33: R | I33: C | J33: A | K33: C
A35: RACI validity checks
B36: Rule | C36: Result | D36: Count of violations
B37: Exactly one A per row | C37: =IF(SUMPRODUCT((COUNTIF(OFFSET(D21,ROW(INDIRECT("1:13"))-1,0,1,8),"A")<>1)*1)=0,"PASS","FAIL") -> PASS | D37: =SUMPRODUCT((COUNTIF(OFFSET(D21,ROW(INDIRECT("1:13"))-1,0,1,8),"A")<>1)*1) -> 0
B38: At least one R per row | C38: =IF(SUMPRODUCT((COUNTIF(OFFSET(D21,ROW(INDIRECT("1:13"))-1,0,1,8),"R")<1)*1)=0,"PASS","FAIL") -> FAIL | D38: =SUMPRODUCT((COUNTIF(OFFSET(D21,ROW(INDIRECT("1:13"))-1,0,1,8),"R")<1)*1) -> 1

Sheet 5_P1_Scope
A1: P1 – Architecture vision: motivation and scope
A2: Purpose | B2: Confirm motivation; choose product family; identify in-scope process stages; capability gap.
A3: Inputs from | B3: P0 readiness band; operating-model choice.
A4: Outputs to | B4: Product family and in-scope stages → P2; capability gap → P3; views V1, V2 → backbone.
A5: RACI summary | B5: R: Sustainability Lead, Procurement Lead; A: Sponsor; C: Enterprise Architect, Legal; I: All.
A6: Phase sign-off | B6: Open | C6: Signed by | E6: please fill | G6: Date | H6: please fill
A8: Problem statement and motivation
B9: Authority-specific problem statement (max 500 chars)
B10: Fraunhofer ISST (Dortmund; around 200 staff; €12.25M annual operating budget) procures approximately 117 staff notebooks on a 3-4 year refresh cycle (€200–400K per cycle) through SAP S/4HANA + SAP Ariba run by central Fraunhofer ICT and authenticated via Microsoft Entra ID. As a contracting authority under EU Directive 2014/24/EU, the institute needs a defensible way to use DPP attributes in market exploration and specification for ICT equipment subject to ESPR.
A12: Drivers and goals
B13: Driver | C13: Weight (1–5) | D13: Linked goal | E13: Goal weight (1–5) | F13: Combined | G13: Origin
B14: ESPR regulatory alignment | C14: 5 | D14: Use DPP attributes lawfully | E14: 5 | F14: =C14*E14 -> 25 | G14: Regulatory
B15: Sustainable procurement strategy | C15: 4 | D15: Lower lifetime energy footprint | E15: 4 | F15: =C15*E15 -> 16 | G15: Strategic
B16: Repairability ambition | C16: 4 | D16: Improve repairability scores | E16: 4 | F16: =C16*E16 -> 16 | G16: Strategic
B17: Auditability requirement | C17: 4 | D17: Capture evidence consistently | E17: 5 | F17: =C17*E17 -> 20 | G17: Operational
B18: Market shaping | C18: 3 | D18: Signal demand for DPP-ready products | E18: 3 | F18: =C18*E18 -> 9 | G18: Strategic
A20: Product family and process stages
B21: Product family (one) | C21: Notebooks
B22: Process stages (mark Y for in-scope)
B23: Need identification | C23: N
B24: Market exploration | C24: Y
B25: Specification authoring | C25: Y
B26: Tender publication | C26: N
B27: Tender evaluation | C27: N
B28: Contract award | C28: N
B29: Contract management | C29: N
B30: Post-award monitoring | C30: N
A32: Capability gap
B33: Capability | C33: Current (1–5) | D33: Target (1–5) | E33: Gap | F33: Notes
B34: Sustainable procurement planning | C34: 3 | D34: 4 | E34: =D34-C34 -> 1
B35: Market exploration | C35: 3 | D35: 4 | E35: =D35-C35 -> 1
B36: Specification authoring | C36: 3 | D36: 5 | E36: =D36-C36 -> 2
B37: Tender evaluation | C37: 4 | D37: 4 | E37: =D37-C37 -> 0
B38: Contract management | C38: 3 | D38: 4 | E38: =D38-C38 -> 1
B39: Data stewardship | C39: 2 | D39: 4 | E39: =D39-C39 -> 2
B40: Enterprise integration | C40: 3 | D40: 4 | E40: =D40-C40 -> 1
B41: Legal compliance assurance | C41: 4 | D41: 4 | E41: =D41-C41 -> 0
B42: Sustainability reporting | C42: 2 | D42: 4 | E42: =D42-C42 -> 2

Sheet 6_P2_Touchpoints
A1: P2 – Process touchpoints and use-case selection
A2: Purpose | B2: Identify procurement process stages × procurement-use roles where DPP data enters; mark priorities.
A3: Inputs from | B3: P1 in-scope process stages.
A4: Outputs to | B4: Touchpoints → R1 (BPMN); priorities → P3 mapping focus.
A5: RACI summary | B5: R: Procurement Lead; A: Sponsor; C: Legal Counsel, Sustainability Lead; I: All.
A6: Phase sign-off | B6: Open | C6: Signed by | E6: please fill | G6: Date | H6: please fill
A8: Touchpoint matrix (priority codes: 0 not used, 1 low, 2 medium, 3 high)
B9: Process stage | C9: Specification | D9: Exclusion | E9: Qualification | F9: Award | G9: Contract clause | H9: Monitoring | I9: Stage priority
B10: Need identification | C10: 0 | D10: 0 | E10: 0 | F10: 0 | G10: 0 | H10: 0 | I10: =MAX(C10:H10) -> 0
B11: Market exploration | C11: 2 | D11: 0 | E11: 0 | F11: 0 | G11: 0 | H11: 0 | I11: =MAX(C11:H11) -> 2
B12: Specification authoring | C12: 3 | D12: 0 | E12: 0 | F12: 0 | G12: 0 | H12: 0 | I12: =MAX(C12:H12) -> 3
B13: Tender publication | C13: 1 | D13: 0 | E13: 0 | F13: 0 | G13: 0 | H13: 0 | I13: =MAX(C13:H13) -> 1
B14: Tender evaluation | C14: 0 | D14: 1 | E14: 2 | F14: 0 | G14: 0 | H14: 0 | I14: =MAX(C14:H14) -> 2
B15: Contract award | C15: 0 | D15: 0 | E15: 0 | F15: 1 | G15: 0 | H15: 0 | I15: =MAX(C15:H15) -> 1
B16: Contract management | C16: 0 | D16: 0 | E16: 0 | F16: 0 | G16: 2 | H16: 1 | I16: =MAX(C16:H16) -> 2
B17: Post-award monitoring | C17: 0 | D17: 0 | E17: 0 | F17: 0 | G17: 0 | H17: 2 | I17: =MAX(C17:H17) -> 2
A19: Award-criterion risk gate
B20: Award marked at least medium anywhere? | C20: =IF(MAX(F10:F17)>=2,"YES","NO") -> NO
B21: Readiness < 3.0? | C21: =IF('3_P0_Readiness'!C37<3,"YES","NO") -> NO
B22: Gate flag | C22: =IF(AND(C20="YES",C21="YES"),"⚠ Gate triggered — downgrade or override required","Pass") -> Pass
B24: Override rationale (≥200 chars)

Sheet 7_P2_Attributes
A1: P2 – Attribute relevance and evidence
A2: Purpose | B2: Score candidate DPP attributes for the in-scope product family. Each attribute carries its scale meaning and provenance (where the attribute and scale come from).
A3: Inputs from | B3: Product family from P1; candidate attribute catalogue (illustrative — see notes below for sources).
A4: Outputs to | B4: Approved attributes → P3 mapping; combined scores → P4 pre-fill.
A5: RACI summary | B5: R: Sustainability Lead, Data Steward; A: Sponsor; C: Enterprise Architect, Legal Counsel; I: All.
A6: Phase sign-off | B6: Open | C6: Signed by | E6: please fill | G6: Date | H6: please fill
A8: Important: the candidate attributes below are illustrative for notebooks/ICT and are derived from existing EU work and certification schemes. They are NOT the final ESPR delegated-act list, which is product-group-specific and is being adopted gradually. Sources are listed per row. Authorities must validate the catalogue against the applicable delegated act when one is in force.
A10: Attribute scoring
B11: DPP attribute | C11: Scale / unit | D11: What the score tells you | E11: R (1–5) | F11: E (1–5) | G11: V (1–5) | H11: wR | I11: wE | J11: wV | K11: Combined | L11: Recommendation
B12: Energy efficiency class | C12: EU Energy Label (A to G) | D12: Indicates labelled energy class against the relevant EU energy label regulation. A=best, G=worst. | E12: 5 | F12: 4 | G12: 5 | H12: 0.4 | I12: 0.4 | J12: 0.2 | K12: =E12*H12+F12*I12+G12*J12 -> 4.6 | L12: =IF(K12>=4,"Use as criterion",IF(K12>=3,"Use for verification","Market exploration only")) -> Use as criterion
B13: Repairability score (where in scope) | C13: Index 0–10 (where adopted) | D13: Aggregate repairability across documentation, ease of disassembly, spare-parts availability, and price of spares. 0 = poorly repairable, 10 = highly repairable. Defined for smartphones/laptops in some Member State regimes; EU-level work is under way under ESPR. | E13: 5 | F13: 4 | G13: 4 | H13: 0.4 | I13: 0.4 | J13: 0.2 | K13: =E13*H13+F13*I13+G13*J13 -> 4.4 | L13: =IF(K13>=4,"Use as criterion",IF(K13>=3,"Use for verification","Market exploration only")) -> Use as criterion
B14: Reliability — guaranteed lifespan | C14: Months / years | D14: Minimum operating lifespan declared and guaranteed by the manufacturer for the product as placed on the market. | E14: 4 | F14: 3 | G14: 3 | H14: 0.4 | I14: 0.4 | J14: 0.2 | K14: =E14*H14+F14*I14+G14*J14 -> 3.4 | L14: =IF(K14>=4,"Use as criterion",IF(K14>=3,"Use for verification","Market exploration only")) -> Use for verification
B15: Recycled content (overall) | C15: % by mass | D15: Percentage of post-consumer recycled material in the product. Subject to definition by product group. | E15: 4 | F15: 3 | G15: 4 | H15: 0.4 | I15: 0.4 | J15: 0.2 | K15: =E15*H15+F15*I15+G15*J15 -> 3.6 | L15: =IF(K15>=4,"Use as criterion",IF(K15>=3,"Use for verification","Market exploration only")) -> Use for verification
B16: Hazardous substance presence | C16: Declaration: Yes / No per substance | D16: Presence of substances of concern (e.g., SCIP database entries, REACH SVHC list). | E16: 4 | F16: 4 | G16: 4 | H16: 0.4 | I16: 0.4 | J16: 0.2 | K16: =E16*H16+F16*I16+G16*J16 -> 4 | L16: =IF(K16>=4,"Use as criterion",IF(K16>=3,"Use for verification","Market exploration only")) -> Use as criterion
B17: Spare parts availability period | C17: Years post-placement | D17: Number of years for which the manufacturer commits to making spare parts available after a product is placed on the market. | E17: 4 | F17: 4 | G17: 4 | H17: 0.4 | I17: 0.4 | J17: 0.2 | K17: =E17*H17+F17*I17+G17*J17 -> 4 | L17: =IF(K17>=4,"Use as criterion",IF(K17>=3,"Use for verification","Market exploration only")) -> Use as criterion
B18: Carbon footprint (PCF) | C18: kg CO2e (cradle-to-gate or full lifecycle, defined by method) | D18: Product Carbon Footprint per declared functional unit. Methodology must be stated. | E18: 4 | F18: 3 | G18: 3 | H18: 0.4 | I18: 0.4 | J18: 0.2 | K18: =E18*H18+F18*I18+G18*J18 -> 3.4 | L18: =IF(K18>=4,"Use as criterion",IF(K18>=3,"Use for verification","Market exploration only")) -> Use for verification
B19: Battery cycle life (where applicable) | C19: Number of cycles to 80% capacity | D19: Cycle life characterising the battery's durability. Applies to products with rechargeable batteries. | E19: 4 | F19: 4 | G19: 3 | H19: 0.4 | I19: 0.4 | J19: 0.2 | K19: =E19*H19+F19*I19+G19*J19 -> 3.8 | L19: =IF(K19>=4,"Use as criterion",IF(K19>=3,"Use for verification","Market exploration only")) -> Use for verification
B20: Conflict-mineral disclosure | C20: Declaration: present / not present | D20: Statement on due diligence relating to tin, tantalum, tungsten, and gold from conflict-affected regions. | E20: 3 | F20: 3 | G20: 3 | H20: 0.4 | I20: 0.4 | J20: 0.2 | K20: =E20*H20+F20*I20+G20*J20 -> 3 | L20: =IF(K20>=4,"Use as criterion",IF(K20>=3,"Use for verification","Market exploration only")) -> Use for verification
B21: End-of-life take-back declaration | C21: Yes / No with route | D21: Supplier's declared route for end-of-life return, reuse, or recycling, including extended producer responsibility scheme membership. | E21: 3 | F21: 4 | G21: 3 | H21: 0.4 | I21: 0.4 | J21: 0.2 | K21: =E21*H21+F21*I21+G21*J21 -> 3.4 | L21: =IF(K21>=4,"Use as criterion",IF(K21>=3,"Use for verification","Market exploration only")) -> Use for verification
A23: Attribute referemce – source of each candidate attribute and scale
B24: Attribute | C24: Source / regulatory or standard origin
B25: Energy efficiency class | C25: EU Energy Labelling Framework Regulation (EU) 2017/1369 and product-specific implementing acts
B26: Repairability score (where in scope)
B27: Reliability — guaranteed lifespan | C27: ESPR
B28: Recycled content (overall) | C28: ESPR Annex I; EU Ecolabel computer criteria 2020/1804 (recycled plastic %).
B29: Hazardous substance presence | C29: REACH Regulation (EC) 1907/2006; ECHA SCIP database
B30: Spare parts availability period | C30: Existing ecodesign implementing acts (e.g., (EU) 2019/2021 for displays) and EU Ecolabel computer criteria.
B31: Carbon footprint (PCF) | C31: ISO 14067; PEF (Product Environmental Footprint) method by EC JRC.
B32: Battery cycle life (where applicable) | C32: EU Batteries Regulation (EU) 2023/1542
B33: Conflict-mineral disclosure | C33: Conflict Minerals Regulation (EU) 2017/821
B34: End-of-life take-back declaration
A36: Summary
B37: # attributes as criterion | C37: =COUNTIF(L12:L21,"Use as criterion") -> 4
B38: # attributes for verification | C38: =COUNTIF(L12:L21,"Use for verification") -> 6
B39: # attributes for exploration only | C39: =COUNTIF(L12:L21,"Market exploration only") -> 0
B40: Mean combined score | C40: =AVERAGE(K12:K21) -> 3.76

Sheet 8_P3_Mapping
A1: P3 – Semantic mapping
A2: Purpose | B2: Map each in-scope DPP attribute to a procurement criterion with mapping type, rule, units, legal note, sign-off.
A3: Inputs from | B3: Approved attributes from P2; legal guidance.
A4: Outputs to | B4: Approved mappings → V4; counts → dashboard indicator.
A5: RACI summary | B5: R: Data Steward; A: Sponsor; C: Sustainability Lead, Legal Counsel, EA; I: All.
A6: Phase sign-off | B6: Open | C6: Signed by | E6: please fill | G6: Date | H6: please fill
A8: Semantic mapping worksheet
B9: DPP attribute | C9: Target procurement criterion | D9: Procurement-use role | E9: Mapping type | F9: Mapping rule | G9: Unit alignment | H9: Legal note | I9: Reviewer | J9: Sign-off date | K9: Status
B10: Repairability score (where in scope) | C10: Minimum repairability threshold | D10: Qualification | E10: Threshold | F10: score >= 7 on the applicable index | G10: OK | H10: Reviewed: scoring methodology referenced | I10: Data Steward | J10: please fill | K10: Approved
B11: Energy efficiency class | C11: Specification minimum energy class | D11: Specification | E11: Direct | F11: class in e.g. A++, A+, A | G11: OK | H11: EU energy label classes are explicit | I11: Data Steward | J11: please fill | K11: Approved
B12: Carbon footprint (PCF) | C12: Comparative metric for evaluation | D12: Specification | E12: Derived | F12: report value, units normalised | G12: OK | H12: Methodology variance noted | I12: Data Steward | J12: please fill | K12: Open
B13: Hazardous substance presence | C13: Exclusion of named substances | D13: Specification | E13: Direct | F13: must declare absence of list X | G13: OK | H13: Aligned with REACH list | I13: Legal Counsel | J13: please fill | K13: Approved
B14: Spare parts availability period | C14: Specification minimum spares lifetime | D14: Specification | E14: Threshold | F14: years >= 7 | G14: OK | H14: Aligned with ESPR scope | I14: Data Steward | J14: please fill | K14: Open
B15: Recycled content (overall) | C15: Award-criterion candidate (gated) | D15: Award (gated) | E15: Threshold | F15: percent >= configurable | G15: OK | H15: Subject to award-criterion risk gate | I15: Legal Counsel | J15: please fill | K15: Open
A18: Validity checks
B19: Rule | C19: Result
B20: No approved mapping with Unit alignment = Mismatch | C20: =IF(SUMPRODUCT((K10:K30="Approved")*(G10:G30="Mismatch"))=0,"PASS","FAIL") -> PASS
B21: Approved coverage % of all rows with data | C21: =IFERROR(COUNTIF(K10:K30,"Approved")/COUNTA(B10:B30),0) -> 0.33333333

Sheet 9_P3_Apps
A1: P3 – Application and information inventory
A2: Purpose | B2: Inventory procurement-supporting applications and information lifecycle for DPP-related data objects.
A3: Inputs from | B3: Application catalogue from P0; mapping outputs from P3.
A4: Outputs to | B4: Inventory and lifecycle
A5: RACI summary | B5: R: Enterprise Architect, IT Integration Lead; A: Sponsor; C: Procurement Lead; I: All.
A6: Phase sign-off | B6: Open | C6: Signed by | E6: please fill | G6: Date | H6: please fill
A8: Application inventory
B9: Application | C9: DPP role | D9: API maturity | E9: Integration readiness (1–5) | F9: Owner role | G9: Notes
B10: SAP Ariba (sourcing & contracts) | C10: Consumer | D10: REST/OData | E10: 4 | F10: Procurement | G10: Hosted by central Fraunhofer ICT
B11: SAP S/4HANA (ERP & purchase requisition) | C11: Consumer | D11: BAPI/OData | E11: 4 | F11: IT | G11: Hosted by central Fraunhofer ICT, ISST consumes shared instance
B12: Microsoft Entra ID (IDP) | C12: Mediator | D12: OIDC/SAML | E12: 5 | F12: IT | G12: Authority-wide identity provider; token issuer for all integrations
B13: DPP Connector microservice | C13: Consumer | D13: REST + IDS dataspace protocol | E13: 4 | F13: IT | G13: Deployed on ISST-operated Kubernetes; brokers dataspace queries
B14: Tender document store (SharePoint) | C14: Consumer | D14: Graph API | E14: 3 | F14: Procurement | G14: Evidence retention; tender file storage
B15: Sustainability reporting tool | C15: Consumer | D15: File import | E15: 2 | F15: Strategy | G15: Local; consolidates indicators for institute reporting
A18: Information lifecycle
B19: Data object | C19: Source | D19: Store | E19: Retention (months) | F19: Retention basis | G19: Access control owner
B20: DPP identifier | C20: External DPP service | D20: Tender record | E20: 60 | F20: Procurement law | G20: Procurement
B21: DPP attribute snapshot | C21: Broker / hub | D21: Tender record | E21: 60 | F21: Audit trail | G21: Data Steward
B22: Evidence reference | C22: Internal tender file | D22: Tender record | E22: 60 | F22: Procurement law | G22: Procurement
B23: Certification reference | C23: External CA | D23: Supplier reg. | E23: 60 | F23: Audit trail | G23: Data Steward
B24: Audit log entry | C24: Broker / hub | D24: Audit store | E24: 60 | F24: Audit trail | G24: IT Integration
A26: Retention check
B27: Minimum retention (months) | C27: 60
B28: All objects meet minimum? | C28: =IF(MIN(E20:E24)>=C27,"PASS","FAIL") -> PASS

Sheet 10_P4_Pattern
A1: P4 – Technology and integration pattern selection
A2: Purpose | B2: Score three patterns on 7 dimensions; weighted total; chosen pattern; rationale.
A3: Inputs from | B3: Readiness (P0); touchpoints (P2); semantic mapping (P3).
A4: Outputs to | B4: → dashboard; → P5 roadmap.
A5: RACI summary | B5: R: Enterprise Architect, IT Integration Lead; A: Sponsor; C: Procurement Lead, Data Steward; I: All.
A6: Phase sign-off | B6: Open | C6: Signed by | E6: please fill | G6: Date | H6: please fill
A8: Pattern scoring matrix (1–5; higher = better; cost-like dimensions are inverted, see Sheet 2 for logic)
B9: Dimension | C9: A: Manual look-up | D9: B: Central database | E9: C: Dataspace connector | F9: Weight
B10: Readiness fit | C10: 5 | D10: 4 | E10: 5 | F10: 0.2
B11: Use-case fit | C11: 2 | D11: 3 | E11: 4 | F11: 0.2
B12: Volume scalability | C12: 1 | D12: 4 | E12: 5 | F12: 0.1
B13: Governance load (inv.) | C13: 5 | D13: 4 | E13: 3 | F13: 0.15
B14: Total cost (inv.) | C14: 5 | D14: 4 | E14: 3 | F14: 0.15
B15: Time-to-value (inv.) | C15: 5 | D15: 4 | E15: 3 | F15: 0.1
B16: Future-proof vs EU portal | C16: 3 | D16: 5 | E16: 5 | F16: 0.1
B17: Weight sum check | C17: =IF(ABS(SUM(F10:F16)-1)<0.01,"PASS (1.00)","FAIL — weights must sum to 1.00") -> PASS (1.00) | F17: =SUM(F10:F16) -> 1
B19: Weighted total | C19: =SUMPRODUCT(C10:C16,$F$10:$F$16) -> 3.8 | D19: =SUMPRODUCT(D10:D16,$F$10:$F$16) -> 3.9 | E19: =SUMPRODUCT(E10:E16,$F$10:$F$16) -> 4
B20: Rank | C20: =RANK(C19,$C$19:$E$19,0) -> 3 | D20: =RANK(D19,$C$19:$E$19,0) -> 2 | E20: =RANK(E19,$C$19:$E$19,0) -> 1
A21: Decision
B22: Chosen pattern | C22: =INDEX({"A: Manual look-up";"B: Central database";"C: Dataspace connector"},MATCH(MAX(C19:E19),C19:E19,0)) -> C: Dataspace connector
B23: Weighted total | C23: =MAX(C19:E19) -> 4
B24: Rationale (≥100 chars)
B25: The following statement relies on availability of the chosen infrastructure. Fraunhofer ISST scores Pattern C highest: 117 notebook users on a 3 to4 year refresh (€200–400K/cycle) running on SAP S/4HANA + SAP Ariba via central Fraunhofer ICT and Microsoft Entra ID, combined with in-house dataspace expertise and existing Kubernetes capability. Pattern A is retained as a contingency. It depends on whether the market/regulatory body has made the infrastructure available..
B27: Low-readiness pattern lock | C27: =IF('3_P0_Readiness'!C37<2,"⚠ Low readiness — Pattern 2b disabled unless override (300-char rationale required)","Pass") -> Pass

Sheet 11_P5_Roadmap
A1: P5 – Transition, work packages, and risks
A2: Purpose | B2: Plateau-based roadmap; work-package register; risk register with RAG.
A3: Inputs from | B3: Pattern (P4); operating model (P0); attribute set (P3).
A4: Outputs to | B4: Roadmap, risks → dashboard.
A5: RACI summary | B5: R: Project Manager; A: Sponsor; C: All; I: External liaisons.
A6: Phase sign-off | B6: Open | C6: Signed by | E6: please fill | G6: Date | H6: please fill
A8: Column legend
B9: M (Month) | C9: Month from project start. M0 = project start. So 'Start (M)=3' means month 3 from project start; 'End (M)=7' means month 7.
B10: PD (Person-days) | C10: Effort estimate in person-days. 1 PD = 1 person working one full day. Aggregates across roles unless a roles split is added in a separate column.
B11: WP (Work package) | C11: A defined unit of delivery with owner, duration, dependencies, and deliverable. IDs increment from WP1.
B12: Lkh / Imp (L / I) | C12: Likelihood and Impact of a risk on a 1–5 scale. Inherent = L × I before safeguard. Residual = same product after safeguard.
B13: RAG | C13: Risk colour band derived from residual score: <6 Green, 6–14 Yellow/Amber, ≥15 Red.
A16: Roadmap — three plateaus
B17: Plateau | C17: Description | I17: Months (M) | L17: Key deliverables
B18: Plateau 0 | C18: Current state: fragmented evidence, manual verification, no DPP touchpoints. | I18: M0 | L18: Baseline catalogue, baseline KPI snapshot.
B19: Plateau 1 | C19: First DPP-enabled use case: single product family, market exploration and specification touchpoints, basic governance. | I19: M0–M9 | L19: Connector R1; mapping R1; first tender.
B20: Plateau 2 | C20: Scaled integration: additional product families, deeper integration, semantic mapping consolidated. | I20: M10–M24 | L20: Pattern re-evaluation; second product family; mapping R2
A22: Work-package register
B23: WP ID | C23: Name | F23: Plateau | G23: Owner role | H23: Start (M) | I23: End (M) | J23: Effort (PD) | K23: Dependencies | L23: Deliverable | O23: Status
B24: WP1 | C24: Governance setup | F24: 1 | G24: Sponsor | H24: 0 | I24: 2 | J24: 10 | K24: — | L24: Charter, RACI | O24: Planned
B25: WP2 | C25: Attribute catalogue v1 | F25: 1 | G25: Sustain Lead | H25: 1 | I25: 4 | J25: 15 | K25: WP1 | L25: Approved attributes | O25: Planned
B26: WP3 | C26: Semantic mapping v1 | F26: 1 | G26: Data Steward | H26: 2 | I26: 5 | J26: 20 | K26: WP2 | L26: Mapping sheet v1 | O26: Planned
B27: WP4 | C27: Dataspace connector deployment | F27: 1 | G27: IT Int. | H27: 3 | I27: 7 | J27: 40 | K27: WP3 | L27: Connector v1 on ISST Kubernetes | O27: Planned
B28: WP5 | C28: First DPP-informed tender | F28: 1 | G28: Proc Lead | H28: 6 | I28: 9 | J28: 20 | K28: WP4 | L28: Tender file | O28: Planned
B29: WP6 | C29: Indicator collection v1 | F29: 1 | G29: Data Steward | H29: 8 | I29: 9 | J29: 10 | K29: WP5 | L29: Indicator set v1 | O29: Planned
B30: WP7 | C30: Second product family scoping | F30: 2 | G30: Proc Lead | H30: 10 | I30: 12 | J30: 15 | K30: WP5 | L30: Scoped package | O30: Planned
B31: WP8 | C31: Mapping v2 consolidation | F31: 2 | G31: Data Steward | H31: 12 | I31: 15 | J31: 25 | K31: WP7 | L31: Mapping v2 | O31: Planned
B32: WP9 | C32: Pattern re-evaluation | F32: 2 | G32: EA | H32: 15 | I32: 18 | J32: 15 | K32: WP6 | L32: Re-scored selection | O32: Planned
A35: Risk register
B36: ID | C36: Risk description | H36: Inh. L | I36: Inh. I | J36: Inh. score | K36: Mitigation / safeguard | M36: Res. L | N36: Res. I | O36: Res. score | P36: RAG
B37: R1 | C37: Legal contestability of repairability scoring | H37: 4 | I37: 5 | J37: =H37*I37 -> 20 | K37: Counsel review, threshold documentation | M37: 3 | N37: 4 | O37: =M37*N37 -> 12 | P37: =IF(O37>=15,"Red",IF(O37>=6,"Amber","Green")) -> Amber
B38: R2 | C38: Dataspace connector maintenance and IDS protocol drift | H38: 4 | I38: 3 | J38: =H38*I38 -> 12 | K38: Versioned connector image; IDSA spec tracking; abstraction layer | M38: 2 | N38: 3 | O38: =M38*N38 -> 6 | P38: =IF(O38>=15,"Red",IF(O38>=6,"Amber","Green")) -> Amber
B39: R3 | C39: SME supplier readiness gap | H39: 4 | I39: 3 | J39: =H39*I39 -> 12 | K39: Lead time; supplier engagement | M39: 3 | N39: 2 | O39: =M39*N39 -> 6 | P39: =IF(O39>=15,"Red",IF(O39>=6,"Amber","Green")) -> Amber
B40: R4 | C40: Cache freshness vs. evidence integrity | H40: 3 | I40: 4 | J40: =H40*I40 -> 12 | K40: Time-stamped snapshots; cache TTL policy | M40: 2 | N40: 3 | O40: =M40*N40 -> 6 | P40: =IF(O40>=15,"Red",IF(O40>=6,"Amber","Green")) -> Amber
B41: R5 | C41: Semantic drift across product families | H41: 3 | I41: 3 | J41: =H41*I41 -> 9 | K41: Mapping v2 consolidation in Plateau 2 | M41: 2 | N41: 2 | O41: =M41*N41 -> 4 | P41: =IF(O41>=15,"Red",IF(O41>=6,"Amber","Green")) -> Green
B42: R6 | C42: EU portal mechanism change | H42: 3 | I42: 4 | J42: =H42*I42 -> 12 | K42: Re-entry of Phase P4 on announcement | M42: 2 | N42: 3 | O42: =M42*N42 -> 6 | P42: =IF(O42>=15,"Red",IF(O42>=6,"Amber","Green")) -> Amber
B43: R7 | C43: Internal audit findings on data lineage | H43: 3 | I43: 4 | J43: =H43*I43 -> 12 | K43: Audit log; retention policy | M43: 2 | N43: 3 | O43: =M43*N43 -> 6 | P43: =IF(O43>=15,"Red",IF(O43>=6,"Amber","Green")) -> Amber

Sheet 12_P6_Evaluation
A1: P6 – Implementation governance and evaluation
A2: Purpose | B2: Define/Evaluate ex-post indicators, capture expert ratings, finalize governance.
A3: Inputs from | B3: All upstream outputs.
A4: Outputs to | B4: Expert evaluation report; indicator catalogue → dashboard.
A5: RACI summary | B5: R: Project Manager; A: Sponsor; C: External experts; I: All.
A6: Phase sign-off | B6: Open
A8: Ex-post adoption indicators
B9: Indicator | C9: Source | D9: Target | E9: Current | F9: Gap | G9: Last review
B10: Mapping coverage (%) | C10: Sheet 8 sign-offs | D10: 90 | E10: 60 | F10: =D10-E10 -> 30 | G10: please fill
B11: Touchpoints active (count) | C11: Sheet 6 priorities | D11: 2 | E11: 1 | F11: =D11-E11 -> 1 | G11: please fill
B12: Approved attributes (count) | C12: Sheet 7 | D12: 5 | E12: 3 | F12: =D12-E12 -> 2 | G12: please fill
B13: Roadmap adherence (%) | C13: Sheet 11 status | D13: 85 | E13: 70 | F13: =D13-E13 -> 15 | G13: please fill
B14: Legal disputes (count) | C14: External record | D14: 0 | E14: 0 | F14: =D14-E14 -> 0 | G14: please fill
B15: Audit findings (count) | C15: External record | D15: 0 | E15: 0 | F15: =D15-E15 -> 0 | G15: please fill
B16: SME participation rate (%) | C16: Tender records | D16: 30 | E16: 28 | F16: =D16-E16 -> 2 | G16: please fill
A18: Implementation governance charter
B19: Body | C19: Steering committee: Sponsor (chair), Procurement Lead, EA, Sustainability Lead, Legal.
B20: Interval | C20: Quarterly; ad-hoc on red risks.
B21: Escalation | C21: Sponsor escalates to executive on red residual risks.

Sheet 13_Reference
A1: Reference data (drop-down lookup sources)
B3: Procurement-use roles
B4: Specification
B5: Exclusion
B6: Qualification
B7: Award
B8: Award (gated)
B9: Contract clause
B10: Monitoring
B12: Mapping types
B13: Direct
B14: Threshold
B15: Derived
... B64: High (>3.5)
